py_gandi_dns_dynip/__init__.py
py_gandi_dns_dynip/main.py
py_gandi_dns_dynip-0.1.4.dist-info/METADATA
py_gandi_dns_dynip-0.1.4.dist-info/WHEEL
py_gandi_dns_dynip-0.1.4.dist-info/entry_points.txt
py_gandi_dns_dynip-0.1.4.dist-info/RECORD
